csvrm/__init__.py
csvrm/exceptions.py
csvrm/fields.py
csvrm/models.py
csvrm-0.2.2.dist-info/LICENSE
csvrm-0.2.2.dist-info/LICENSE.txt
csvrm-0.2.2.dist-info/METADATA
csvrm-0.2.2.dist-info/WHEEL
csvrm-0.2.2.dist-info/top_level.txt
csvrm-0.2.2.dist-info/RECORD
