Metadata-Version: 2.1
Name: csvrm
Version: 0.2.2
License-File: LICENSE
License-File: LICENSE.txt
